MANIFEST.in
README.md
requirements.txt
setup.py
pygvideo/__init__.py
pygvideo/_constants.py
pygvideo/_pygvideo.py
pygvideo/_utils.py
pygvideo/_version.py
pygvideo/_video_preview.py
pygvideo.egg-info/PKG-INFO
pygvideo.egg-info/SOURCES.txt
pygvideo.egg-info/dependency_links.txt
pygvideo.egg-info/requires.txt
pygvideo.egg-info/top_level.txt