Metadata-Version: 2.1
Name: pygvideo
Version: 1.4.0
Summary: pygvideo, video for pygame. Using moviepy video module to read and organize videos.
Home-page: https://github.com/azzammuhyala/pygvideo.git
Author: azzammuhyala
Author-email: azzammuhyala@gmail.com
License: MIT
Keywords: pygvideo,pygamevid,pyvidplayer,pygame vid,pygame video,video player,vid player,pygame player,python pygame video,pgvideo,pgvid,video,player,pygame video player
Classifier: Programming Language :: Python :: 3
Classifier: Programming Language :: Python :: 3.10
Classifier: Operating System :: OS Independent
Classifier: License :: OSI Approved :: MIT License
Classifier: Topic :: Multimedia
Classifier: Topic :: Multimedia :: Sound/Audio
Classifier: Topic :: Multimedia :: Sound/Audio :: Analysis
Classifier: Topic :: Multimedia :: Video
Classifier: Topic :: Multimedia :: Video :: Capture
Classifier: Topic :: Multimedia :: Video :: Conversion
Requires-Python: >=3.10
Requires-Dist: pygame>=2.5.0
Requires-Dist: moviepy>=2.1.1
